apigw_wsgi_handler.py
apigw_wsgi_handler-1.0.0.dist-info/DESCRIPTION.rst
apigw_wsgi_handler-1.0.0.dist-info/LICENSE.txt
apigw_wsgi_handler-1.0.0.dist-info/METADATA
apigw_wsgi_handler-1.0.0.dist-info/RECORD
apigw_wsgi_handler-1.0.0.dist-info/WHEEL
apigw_wsgi_handler-1.0.0.dist-info/metadata.json
apigw_wsgi_handler-1.0.0.dist-info/top_level.txt
