Metadata-Version: 2.0
Name: apigw-wsgi-handler
Version: 1.0.0
Summary: Python 2 and 3 compatibility utilities
Home-page: http://pypi.python.org/pypi/apigw-wsgi-handler/
Author: Artyom Topchyan
Author-email: artyom.topchyan@live.com
License: MIT
Platform: UNKNOWN
Classifier: Programming Language :: Python :: 2
Classifier: Programming Language :: Python :: 3
Classifier: Intended Audience :: Developers
Classifier: License :: OSI Approved :: MIT License
Classifier: Topic :: Software Development :: Libraries
Classifier: Topic :: Utilities
Requires-Dist: Werkzeug (>=0.9)
